gli99/__init__.py
gli99/browser_options.json
gli99/tools.py
gli99-1.1.10.dist-info/LICENSE.txt
gli99-1.1.10.dist-info/METADATA
gli99-1.1.10.dist-info/WHEEL
gli99-1.1.10.dist-info/top_level.txt
gli99-1.1.10.dist-info/RECORD
