Metadata-Version: 2.1
Name: gli99
Version: 1.1.10
Summary: Web scraper for gifcities.org
Home-page: https://github.com/TomTkacz/gli99
Author: Tom Tkacz
Author-email: thomasatkacz@gmail.com
Classifier: Programming Language :: Python
Classifier: Programming Language :: Python :: 3.10
Classifier: License :: OSI Approved :: MIT License
Classifier: Operating System :: OS Independent
Requires-Python: >3.10.0
License-File: LICENSE.txt
Requires-Dist: selenium
Requires-Dist: requests
Requires-Dist: webdriver-manager
